jentic/apitools/openapi/transformer/bundler/backends/redocly/__init__.py
jentic/apitools/openapi/transformer/bundler/backends/redocly/py.typed
jentic_openapi_transformer_redocly-1.0.0a34.dist-info/licenses/LICENSE
jentic_openapi_transformer_redocly-1.0.0a34.dist-info/licenses/NOTICE
jentic_openapi_transformer_redocly-1.0.0a34.dist-info/WHEEL
jentic_openapi_transformer_redocly-1.0.0a34.dist-info/entry_points.txt
jentic_openapi_transformer_redocly-1.0.0a34.dist-info/METADATA
jentic_openapi_transformer_redocly-1.0.0a34.dist-info/RECORD
