Metadata-Version: 2.4
Name: jentic-openapi-transformer-redocly
Version: 1.0.0a34
Summary: Jentic OpenAPI Redocly Transformer Backend
Author: Jentic
Author-email: Jentic <hello@jentic.com>
License-Expression: Apache-2.0
License-File: LICENSE
License-File: NOTICE
Requires-Dist: jentic-openapi-common~=1.0.0a34
Requires-Dist: jentic-openapi-transformer~=1.0.0a34
Requires-Python: >=3.11
Project-URL: Homepage, https://github.com/jentic/jentic-openapi-tools
